thinrest/__init__.py
thinrest/api.py
thinrest/models.py
thinrest/urls.py
thinrest/fixtures/__init__.py
thinrest/fixtures/sample.json
thinrest/migrations/0001_initial.py
thinrest/migrations/__init__.py
thinrest/tests/__init__.py
thinrest/tests/employee.py
thinrest/tests/systemsetting.py
thinrest-2.0.0.dist-info/DESCRIPTION.rst
thinrest-2.0.0.dist-info/METADATA
thinrest-2.0.0.dist-info/RECORD
thinrest-2.0.0.dist-info/WHEEL
thinrest-2.0.0.dist-info/metadata.json
thinrest-2.0.0.dist-info/top_level.txt
