Metadata-Version: 2.0
Name: thinrest
Version: 2.0.0
Summary: Rest implementation using Tastypie.
Home-page: https://github.com/anuragal/thinrest
Author: Anurag Agarwal
Author-email: anurag26@gmail.com
License: The MIT License (MIT)
Requires-Dist: Django (==1.5.12)
Requires-Dist: South (>=0.7.6)
Requires-Dist: django-tastypie (>=0.12.2)
